gajja/__init__.py
gajja-0.1.4.dist-info/DESCRIPTION.rst
gajja-0.1.4.dist-info/METADATA
gajja-0.1.4.dist-info/RECORD
gajja-0.1.4.dist-info/WHEEL
gajja-0.1.4.dist-info/metadata.json
gajja-0.1.4.dist-info/top_level.txt
