Metadata-Version: 2.0
Name: gajja
Version: 0.1.4
Summary: Gajja: Fake objects for real tests.
Home-page: https://pagure.io/python-gajja
Author: Ben Finney
Author-email: ben+python@benfinney.id.au
License: GPLv3+
Keywords: test,double,fake,mock,filesystem,subprocess
Platform: UNKNOWN
Classifier: Development Status :: 3 - Alpha
Classifier: License :: OSI Approved :: GNU General Public License v3 or later (GPLv3+)
Classifier: Operating System :: POSIX
Classifier: Programming Language :: Python :: 2.7
Classifier: Programming Language :: Python :: 3.3
Classifier: Programming Language :: Python :: 3.4
Classifier: Programming Language :: Python :: 3.5
Classifier: Intended Audience :: Developers
Classifier: Topic :: Software Development :: Testing
Requires-Dist: mock (>=1.3)
Requires-Dist: setuptools
Requires-Dist: testtools
Requires-Dist: unittest2 (>=0.5.1)
